{"cameraMode":{"drawMode":0,"name":"Shaded","section":"Shading Mode"},"sceneLighting":false,"audioPlay":false,"sceneViewState":{"m_AlwaysRefresh":false,"showFog":true,"showSkybox":false,"showFlares":true,"showImageEffects":true,"showParticleSystems":true,"showVisualEffectGraphs":true,"m_FxEnabled":true},"in2DMode":false,"pivot":{"x":13.793777465820313,"y":6.023099899291992,"z":4.656869888305664},"rotation":{"x":-0.05232137814164162,"y":-0.5305144190788269,"z":0.032834429293870929,"w":-0.8454271554946899},"size":21.81892204284668,"orthographic":false}