{"cameraMode":{"drawMode":0,"name":"Shaded","section":"Shading Mode"},"sceneLighting":false,"audioPlay":false,"sceneViewState":{"m_AlwaysRefresh":false,"showFog":true,"showSkybox":false,"showFlares":true,"showImageEffects":true,"showParticleSystems":true,"showVisualEffectGraphs":true,"m_FxEnabled":true},"in2DMode":false,"pivot":{"x":-0.07742786407470703,"y":7.3712921142578129,"z":-0.30755770206451418},"rotation":{"x":-0.10893073678016663,"y":-0.7177708148956299,"z":0.11532469093799591,"w":-0.6779741644859314},"size":7.460059642791748,"orthographic":false}